{
  "TBL": {
    "Studies": {
      "blockTitle": "Education",
      "items": [
        {
          "id": "study1",
          "title": "Scientific Baccalaureate",
          "subtitle": "Engineering Sciences",
          "date": "2012 - 2013"
        },
        {
          "id": "study2",
          "title": "Web Integrator Diploma",
          "subtitle": "OpenClassrooms",
          "text": "Acquired skills through 12 validated web development projects. Training focused on CSS/SCSS, HTML, JavaScript, SEO, and React/Redux.",
          "date": "2023-2024"
        },
        {
          "id": "study3",
          "title": "Electric Equipment Operation",
          "subtitle": "Auchan",
          "text": "Training in operating electric pallet trucks and stackers.",
          "date": "2024 - 2025"
        }
      ]
    },
    "Experiences": {
      "blockTitle": "Experience",
      "items": [
        {
          "id": "exp1",
          "title": "Head of Design",
          "subtitle": "CreatLinx, London",
          "text": "Co-founder of a blockchain/cryptocurrency startup. Responsible for recruitment, design validation, development, and strategic planning. Soft skills: versatility, adaptability, creativity.",
          "date": "2017 - 2019"
        },
        {
          "id": "exp2",
          "title": "Entertainer & Bartender",
          "subtitle": "Huttopia, Rillé",
          "text": "Entertainer for children and families as well as bartender at a campsite during the summer season.",
          "date": "2019"
        },
        {
          "id": "exp3",
          "title": "Barista",
          "subtitle": "Columbus, Strasbourg",
          "text": "Prepared and served hot and cold beverages along with pastries, managed cash transactions, and maintained cleanliness of the premises.",
          "date": "2019"
        },
        {
          "id": "exp4",
          "title": "Cook & Waiter",
          "subtitle": "Factory & Co, Strasbourg",
          "text": "Independently or collaboratively prepared dishes. Demonstrated proficiency in assembling and cooking burgers, bagels, and salads. Managed order taking, table service, cash handling, and maintenance of the premises.",
          "date": "2019 - 2022"
        },
        {
          "id": "exp5",
          "title": "Retail Associate",
          "subtitle": "Auchan, Illkirch",
          "text": "Versatile employee in a supermarket's maintenance team. Responsible for restocking and maintaining shelves, assisting customers, and handling stock. Received training on specialized equipment.",
          "date": "2024 - 2025"
        }
      ]
    },
    "Hobbies": {
      "blockTitle": "Interests",
      "items": [
        {
          "id": "hob1",
          "title": "Music",
          "text": "Guitar, piano, pad, Digital Audio Workstation (advanced proficiency in FL Studio and various audio plugins)."
        }
      ]
    },
    "Profil": {
      "blockTitle": "Profile",
      "items": [
        {
          "id": "prof1",
          "title": "Profile",
          "text": "With a solid background in restaurant and customer service, I have worked as a barista and in various service roles. I have developed versatility, efficiency, and a strong sense of customer satisfaction. I aim to leverage my interpersonal skills and contribute to a friendly and dynamic environment. Simultaneously, I am engaged in freelance web development, an activity that fuels my curiosity and nurtures my creativity."
        }
      ]
    }
  },
  "DTL": {
    "Contact": {
      "blockTitle": "Contact",
      "items": [
        {
          "id": "cf0",
          "icon": "faGlobe",
          "text": "erwanrobin.com"
        },
        {
          "id": "cf1",
          "icon": "faLinkedinIn",
          "text": "Erwan Robin"
        },
        {
          "id": "cf2",
          "icon": "faGithub",
          "text": "ErwanRob"
        },
        {
          "id": "cf3",
          "icon": "faInstagram",
          "text": "erwan.rob"
        },
        {
          "id": "cf4",
          "icon": "faEarthEurope",
          "text": "France"
        },
        {
          "id": "cf5",
          "icon": "faHome",
          "text": "Strasbourg (67)"
        },
        {
          "id": "cf6",
          "icon": "faPhone",
          "text": "06 10 50 28 37"
        },
        {
          "id": "cf7",
          "icon": "faEnvelope",
          "text": "erobin.contact@gmail.com"
        }
      ]
    },
    "Socials": {
      "blockTitle": "Links",
      "items": [
        {
          "id": "sc1",
          "icon": "faGithub",
          "text": "ErwanRob"
        },
        {
          "id": "sc2",
          "icon": "faLinkedinIn",
          "text": "Erwan Robin"
        },
        {
          "id": "sc3",
          "icon": "faInstagram",
          "text": "erwan.rob"
        }
      ]
    },
    "Values": {
      "blockTitle": "Soft Skills",
      "items": [
        {
          "id": "val1",
          "text": "Autonomy"
        },
        {
          "id": "val2",
          "text": "Communication"
        },
        {
          "id": "val3",
          "text": "Team Spirit"
        },
        {
          "id": "val4",
          "text": "Perseverance"
        }
      ]
    },
    "Skills": {
      "blockTitle": "Skills",
      "items": [
        {
          "id": "sk1",
          "text": "Service"
        },
        {
          "id": "sk2",
          "text": "Customer Relations"
        },
        {
          "id": "sk3",
          "text": "Hygiene Standards"
        },
        {
          "id": "sk4",
          "text": "Material Handling"
        }
      ]
    },
    "Language": {
      "blockTitle": "Languages",
      "items": [
        {
          "id": "lang1",
          "text": "French"
        },
        {
          "id": "lang2",
          "text": "English (advanced)"
        }
      ]
    }
  }
}
